README.md
setup.py
onnpdf/__init__.py
onnpdf/pdf.py
onnpdf.egg-info/PKG-INFO
onnpdf.egg-info/SOURCES.txt
onnpdf.egg-info/dependency_links.txt
onnpdf.egg-info/requires.txt
onnpdf.egg-info/top_level.txt