Metadata-Version: 2.1
Name: onnpdf
Version: 0.0.1
Summary: Convenience Python module for creating templated PDF documents
Home-page: http://oznetnerd.com
Author: Will Robinson
Author-email: will@oznetnerd.com
License: UNKNOWN
Platform: UNKNOWN
